pyprogress/__init__.py
pyprogress/progress.py
pyprogress_elunico-0.1.6.dist-info/LICENSE
pyprogress_elunico-0.1.6.dist-info/METADATA
pyprogress_elunico-0.1.6.dist-info/WHEEL
pyprogress_elunico-0.1.6.dist-info/top_level.txt
pyprogress_elunico-0.1.6.dist-info/RECORD
