Metadata-Version: 2.1
Name: pyprogress-elunico
Version: 0.1.6
Summary: A terminal progress printing utility
Home-page: https://github.com/elunico/pyprogress
Author: Thomas Povinelli
Author-email: tompov227@gmail.com
Keywords: progress bar terminal
Classifier: Programming Language :: Python :: 3
Classifier: License :: OSI Approved :: MIT License
Classifier: Operating System :: OS Independent
Requires-Python: >=3.6
License-File: LICENSE
